fluidattacks_utils_logger/__init__.py
fluidattacks_utils_logger/env.py
fluidattacks_utils_logger/handlers.py
fluidattacks_utils_logger/levels.py
fluidattacks_utils_logger/logger.py
fluidattacks_utils_logger/py.typed
fluidattacks_utils_logger-2.1.1.dist-info/WHEEL
fluidattacks_utils_logger-2.1.1.dist-info/METADATA
fluidattacks_utils_logger-2.1.1.dist-info/RECORD
