Metadata-Version: 2.4
Name: fluidattacks_utils_logger
Version: 2.1.1
Summary: Common logger handlers
Author-email: Product Team <development@fluidattacks.com>
Requires-Python: >=3.11
Classifier: License :: OSI Approved :: MIT License
Requires-Dist: bugsnag >=4.7.0, <5.0.0
Requires-Dist: fluidattacks-core >=4.0.0, <5.0.0
Requires-Dist: fa-purity >=2.5.2, <3.0.0
